shua/struct/__init__.py
shua/struct/extensions/__init__.py
shua/struct/extensions/bytes.py
shua/struct/extensions/numeric.py
shua/struct/field.py
shua/struct/struct.py
shua_struct-0.2.0.dist-info/METADATA
shua_struct-0.2.0.dist-info/WHEEL
shua_struct-0.2.0.dist-info/entry_points.txt
shua_struct-0.2.0.dist-info/licenses/LICENSE
shua_struct-0.2.0.dist-info/RECORD
