Metadata-Version: 2.1
Name: shua_struct
Version: 0.2.0
Summary: Flexible binary data parsing and building for Python.
Author-Email: Shua-github <CHA_shua@outlook.com>
License: MIT
Project-URL: Repository, https://github.com/shua-github/shua_struct
Requires-Python: >=3.11
